sallmon_wallet/__init__.py
sallmon_wallet/cli.py
sallmon_wallet/config.py
sallmon_wallet/test-cli.py
sallmon_wallet/test-utxo.py
sallmon_wallet/test-wallet.py
sallmon_wallet/utils.py
sallmon_wallet/commands/__init__.py
sallmon_wallet/commands/balance.py
sallmon_wallet/commands/mempool.py
sallmon_wallet/commands/mining.py
sallmon_wallet/commands/utxo.py
sallmon_wallet/commands/wallet.py
sallmon_wallet/services/__init__.py
sallmon_wallet/services/database.py
sallmon_wallet/utils/__init__.py
sallmon_wallet/utils/blockchain.py
sallmon_wallet/utils/encryption.py
sallmon_wallet-1.0.1.dist-info/METADATA
sallmon_wallet-1.0.1.dist-info/WHEEL
sallmon_wallet-1.0.1.dist-info/entry_points.txt
sallmon_wallet-1.0.1.dist-info/top_level.txt
sallmon_wallet-1.0.1.dist-info/RECORD
