Metadata-Version: 2.1
Name: sallmon-wallet
Version: 1.0.1
Summary: Sallmon Wallet CLI for cryptocurrency wallet management and blockchain integration.
Home-page: https://github.com/minakilabs/sallmon-sdk
Author: Andrew Polykandriotis
Author-email: andrew@minakilabs.com
License: UNKNOWN
Platform: UNKNOWN
Classifier: Programming Language :: Python :: 3
Classifier: License :: OSI Approved :: MIT License
Classifier: Operating System :: OS Independent
Requires-Python: >=3.7
Requires-Dist: base58
Requires-Dist: click
Requires-Dist: cryptography
Requires-Dist: ecdsa
Requires-Dist: requests
